scopesim/__init__.py
scopesim/commands/__init__.py
scopesim/commands/scopesimple.py
scopesim/commands/user_commands.py
scopesim/data/svo/2MASS/2MASS.H.xml
scopesim/data/svo/2MASS/2MASS.J.xml
scopesim/data/svo/2MASS/2MASS.Ks.xml
scopesim/data/svo/GTC/OSIRIS.F643.xml
scopesim/data/svo/GTC/OSIRIS.F643_filter.xml
scopesim/data/svo/GTC/OSIRIS.F648.xml
scopesim/data/svo/GTC/OSIRIS.F648_filter.xml
scopesim/data/svo/GTC/OSIRIS.F657.xml
scopesim/data/svo/GTC/OSIRIS.F657_filter.xml
scopesim/data/svo/GTC/OSIRIS.F666.xml
scopesim/data/svo/GTC/OSIRIS.F666_filter.xml
scopesim/data/svo/GTC/OSIRIS.F680.xml
scopesim/data/svo/GTC/OSIRIS.F680_filter.xml
scopesim/data/svo/GTC/OSIRIS.F694.xml
scopesim/data/svo/GTC/OSIRIS.F694_filter.xml
scopesim/data/svo/GTC/OSIRIS.F709.xml
scopesim/data/svo/GTC/OSIRIS.F709_filter.xml
scopesim/data/svo/GTC/OSIRIS.F723.xml
scopesim/data/svo/GTC/OSIRIS.F723_filter.xml
scopesim/data/svo/GTC/OSIRIS.F738.xml
scopesim/data/svo/GTC/OSIRIS.F738_filter.xml
scopesim/data/svo/GTC/OSIRIS.F754.xml
scopesim/data/svo/GTC/OSIRIS.F754_filter.xml
scopesim/data/svo/GTC/OSIRIS.F770.xml
scopesim/data/svo/GTC/OSIRIS.F770_filter.xml
scopesim/data/svo/GTC/OSIRIS.F785.xml
scopesim/data/svo/GTC/OSIRIS.F785_filter.xml
scopesim/data/svo/GTC/OSIRIS.F802.xml
scopesim/data/svo/GTC/OSIRIS.F802_filter.xml
scopesim/data/svo/GTC/OSIRIS.F819.xml
scopesim/data/svo/GTC/OSIRIS.F819_filter.xml
scopesim/data/svo/GTC/OSIRIS.F838.xml
scopesim/data/svo/GTC/OSIRIS.F838_filter.xml
scopesim/data/svo/GTC/OSIRIS.F858.xml
scopesim/data/svo/GTC/OSIRIS.F858_filter.xml
scopesim/data/svo/GTC/OSIRIS.F878.xml
scopesim/data/svo/GTC/OSIRIS.F878_filter.xml
scopesim/data/svo/GTC/OSIRIS.F893.xml
scopesim/data/svo/GTC/OSIRIS.F893_filter.xml
scopesim/data/svo/GTC/OSIRIS.F902.xml
scopesim/data/svo/GTC/OSIRIS.F902_filter.xml
scopesim/data/svo/GTC/OSIRIS.F911.xml
scopesim/data/svo/GTC/OSIRIS.F911_filter.xml
scopesim/data/svo/GTC/OSIRIS.F919.xml
scopesim/data/svo/GTC/OSIRIS.F919_filter.xml
scopesim-0.11.2.dist-info/LICENSE
scopesim-0.11.2.dist-info/METADATA
scopesim-0.11.2.dist-info/WHEEL
scopesim-0.11.2.dist-info/RECORD
