Metadata-Version: 2.3
Name: ScopeSim
Version: 0.11.2
Summary: Generalised telescope observation simulator
License: GPL-3.0-or-later
Keywords: astronomy
Author: Kieran Leschinski
Author-email: kieran.leschinski@univie.ac.at
Maintainer: Kieran Leschinski
Maintainer-email: kieran.leschinski@univie.ac.at
Requires-Python: >=3.10,<3.15
Classifier: Intended Audience :: Science/Research
Classifier: License :: OSI Approved :: GNU General Public License v3 or later (GPLv3+)
Classifier: Operating System :: OS Independent
Classifier: Programming Language :: Python :: 3
Classifier: Programming Language :: Python :: 3.10
Classifier: Programming Language :: Python :: 3.11
Classifier: Programming Language :: Python :: 3.12
Classifier: Programming Language :: Python :: 3.13
Classifier: Topic :: Scientific/Engineering :: Astronomy
Requires-Dist: anisocado (>=0.5.0,<1.0)
Requires-Dist: astar-utils (>=0.5.0,<1.0)
Requires-Dist: astropy (>=6.1.7,<8.0.0)
Requires-Dist: beautifulsoup4 (>=4.13.3,<5.0.0)
Requires-Dist: docutils (>=0.19,<1.0)
Requires-Dist: httpx (>=0.28.1,<1.0)
Requires-Dist: lxml (>=6.0.2,<7.0.0)
Requires-Dist: matplotlib (>=3.10.5,<4.0.0)
Requires-Dist: more-itertools (>=10.2.0,<11.0.0)
Requires-Dist: numpy (>=1.26.4,<2.3.0) ; python_version >= "3.10" and python_version < "3.13"
Requires-Dist: numpy (>=2.2.6,<3.0.0) ; python_version >= "3.13"
Requires-Dist: packaging (>=25.0,<26.0)
Requires-Dist: pooch (>=1.8.2,<2.0.0)
Requires-Dist: pyyaml (>=6.0.3,<7.0.0)
Requires-Dist: scipy (>=1.15.3,<1.16.0) ; python_version == "3.10"
Requires-Dist: scipy (>=1.17.0,<1.18.0) ; python_version >= "3.11"
Requires-Dist: skycalc-ipy (>=0.7.0,<1.0)
Requires-Dist: synphot (>=1.5.0,<2.0.0)
Requires-Dist: tqdm (>=4.66.6,<5.0.0)
Project-URL: Bug Tracker, https://github.com/AstarVienna/ScopeSim/issues
Project-URL: Changelog, https://github.com/AstarVienna/ScopeSim/blob/main/CHANGELOG.md
Project-URL: Documentation, https://scopesim.readthedocs.io/en/latest/
Project-URL: Repository, https://github.com/AstarVienna/ScopeSim
